{
    "interface_version": 2,
    "name": "BQMaaDNA",
    "title": "BQMaaDNA",
    "description": "这是一个BQ使用 MaaFramework 创建的二重螺旋自动化脚本。",
    "icon": "./resource/image/logo.ico",
    "contact": "QQ群: 123456789",
    "license": "MIT",
    "welcome": "首次使用！欢迎使用 BQMaaDNA!",
    // 填写项目地址和版本号可实现自动更新功能
    "github": "https://github.com/BQOvO/BQmaaDNA",
    "version": "1.1.1",
    // Mirror酱为第三方分发服务，新项目默认关闭
    // 若有需要请联系 Mirror酱 开通，直接自行开启是无法使用的
    // "mirrorchyan_rid": "MaaXXX",
    // "mirrorchyan_multiplatform": true,
    "controller": [
        {
            "name": "模拟器",
            "type": "Adb",
            "display_short_side": 720 // 默认缩放分辨率的短边长度
        }
    ],
    "resource": [
        {
            "name": "模拟器",
            "path": [
                "./resource"
            ]
        }
    ],
    "task": [
        {
            "name": "魔之楔驱离",
            "entry": "quli",
            "option": ["魔之楔挑战等级","使用绿书"],
            "default_check": false,
            "description": "# !!!注意事项\n1.该任务目前仅支持黎瑟主控\n2.请在开始挑战页面开始执行本任务"
        },
        {
            "name":"委托密函",
            "entry": "weituomihan",
            "option": ["挑战类型"],
            "default_check": false
        }
    ],
    "option": {
        "魔之楔挑战等级":{
            "type": "select",
            "label": "魔之楔挑战等级",
            "default_case": "Lv.40",
            "cases": [
                {
                    "name": "Lv.40",
                    "pipeline_override": {
                        "quli": {
                            "next": "quli40"
                        }
                    }
                },
                {
                    "name": "Lv.60",
                    "pipeline_override": {
                        "quli":{
                            "next": "quli60"
                        }
                    }
                },
                {
                    "name": "Lv.80",
                    "pipeline_override": {
                        "quli":{
                            "next": "quli80"
                        }
                    }
                },
                {
                    "name": "Lv.100",
                    "pipeline_override": {
                        "quli":{
                            "next": "quli100"
                        }
                    }
                }
            ]
        },
        "使用绿书":{
            "type": "switch",
            "cases": [
                {
                    "name": "Yes",
                    "pipeline_override": {
                        "开始挑战1": {
                            "next": "使用绿书"
                        },
                        "驱离-寻路-点击再次开始": {
                            "next": "使用绿书"
                        }
                    }
                },
                {
                    "name": "No",
                    "pipeline_override": {
                        "开始挑战1": {
                            "next": "开始挑战2"
                        },
                        "驱离-寻路-再次进行": {
                            "next": "开始挑战3"
                        }
                    }
                }
            ]
        },
        "挑战类型":{
            "type": "select",
            "label": "挑战类型",
            "default_case": "探险/无尽",
            "cases": [
                {
                    "name": "探险/无尽",
                    "pipeline_override": {
                        "weituomihan": {
                            "next": "探险/无尽"
                        }
                    }
                }
            ]
        }
        }
}
