{
    "夜航-55-1": {
        "recognition": "OCR",
        "expected": [
            "舍身蒙恩的神甫"
        ],
        "replace": [
            [
                "\\s+",
                ""
            ]
        ],
        "pre_delay": 0,
        "action": "Custom",
        "custom_action": "VoyageClick",
        "post_delay": 0
    },
    "夜航-55-2": {
        "recognition": "OCR",
        "expected": [
            "爆破蒙恩的先锋"
        ],
        "replace": [
            [
                "\\s+",
                ""
            ]
        ],
        "pre_delay": 0,
        "action": "Custom",
        "custom_action": "VoyageClick",
        "post_delay": 0
    },
    "夜航-55-3": {
        "recognition": "OCR",
        "expected": [
            "猩红蒙恩的执事"
        ],
        "replace": [
            [
                "\\s+",
                ""
            ]
        ],
        "pre_delay": 0,
        "action": "Custom",
        "custom_action": "VoyageClick",
        "post_delay": 0
    },
    "夜航-55-4": {
        "recognition": "OCR",
        "expected": [
            "枯萎蒙恩的神甫"
        ],
        "replace": [
            [
                "\\s+",
                ""
            ]
        ],
        "pre_delay": 0,
        "action": "Custom",
        "custom_action": "VoyageClick",
        "post_delay": 0
    },
    "夜航-55-5": {
        "recognition": "OCR",
        "expected": [
            "残火蒙恩的先锋"
        ],
        "replace": [
            [
                "\\s+",
                ""
            ]
        ],
        "pre_delay": 0,
        "action": "Custom",
        "custom_action": "VoyageClick",
        "post_delay": 0
    },
    "夜航-55-6": {
        "recognition": "DirectHit",
        "action": "Swipe",
        "begin": [
            600,
            500
        ],
        "end": [
            [
                600,
                135
            ]
        ],
        "duration": [
            1500
        ],
        "post_delay": 1000,
        "next": [
            "夜航-55-6-2"
        ]
    },
    "夜航-55-6-2": {
        "recognition": "OCR",
        "expected": [
            "舍身蒙恩的执事"
        ],
        "replace": [
            [
                "\\s+",
                ""
            ]
        ],
        "pre_delay": 0,
        "action": "Custom",
        "custom_action": "VoyageClick",
        "post_delay": 0
    }
}